sceptre/__init__.py
sceptre/connection_manager.py
sceptre/context.py
sceptre/exceptions.py
sceptre/helpers.py
sceptre/stack.py
sceptre/stack_status.py
sceptre/template.py
sceptre/config/__init__.py
sceptre/config/graph.py
sceptre/config/reader.py
sceptre/config/strategies.py
sceptre/hooks/__init__.py
sceptre/plan/__init__.py
sceptre/plan/actions.py
sceptre/plan/executor.py
sceptre/plan/plan.py
sceptre/resolvers/__init__.py
sceptre/stack_policies/lock.json
sceptre/stack_policies/unlock.json
sceptre_core-0.0.2.data/data/sceptre/stack_policies/lock.json
sceptre_core-0.0.2.data/data/sceptre/stack_policies/unlock.json
sceptre_core-0.0.2.dist-info/LICENSE
sceptre_core-0.0.2.dist-info/METADATA
sceptre_core-0.0.2.dist-info/NOTICE
sceptre_core-0.0.2.dist-info/WHEEL
sceptre_core-0.0.2.dist-info/top_level.txt
sceptre_core-0.0.2.dist-info/RECORD
