Metadata-Version: 2.1
Name: sceptre-core
Version: 0.0.2
Summary: Cloud Provisioning Tool
Home-page: https://github.com/cloudreach/sceptre
Author: Cloudreach
Author-email: sceptre@cloudreach.com
License: Apache2
Keywords: sceptre
Platform: UNKNOWN
Classifier: Development Status :: 5 - Production/Stable
Classifier: Intended Audience :: Developers
Classifier: Natural Language :: English
Classifier: Environment :: Console
Classifier: Programming Language :: Python :: 2.7
Classifier: Programming Language :: Python :: 3.5
Classifier: Programming Language :: Python :: 3.6
Classifier: Programming Language :: Python :: 3.7
Requires-Dist: boto3 (<2.0,>=1.3)
Requires-Dist: PyYaml (<6.0,>=5.1)
Requires-Dist: Jinja2 (<3,>=2.8)
Requires-Dist: packaging (==16.8)
Requires-Dist: six (<2.0.0,>=1.11.0)
Requires-Dist: networkx (==2.1)
Provides-Extra: test
Requires-Dist: pytest (>=3.2) ; extra == 'test'
Requires-Dist: troposphere (>=2.0.0) ; extra == 'test'
Requires-Dist: moto (==1.3.8) ; extra == 'test'
Requires-Dist: mock (==2.0.0) ; extra == 'test'
Requires-Dist: behave (==1.2.5) ; extra == 'test'
Requires-Dist: freezegun (==0.3.12) ; extra == 'test'
Requires-Dist: sceptre-aws-stackoutput-external-resolver (==1.0.0) ; extra == 'test'
Requires-Dist: sceptre-aws-stackoutput-resolver (==1.0.0) ; extra == 'test'
